setup.cfg
setup.py
SmslsUtils.egg-info/PKG-INFO
SmslsUtils.egg-info/SOURCES.txt
SmslsUtils.egg-info/dependency_links.txt
SmslsUtils.egg-info/not-zip-safe
SmslsUtils.egg-info/requires.txt
SmslsUtils.egg-info/top_level.txt
SmslsUtils/DataTools/CsvLogger.py
SmslsUtils/DataTools/DataPlotter.py
SmslsUtils/DataTools/FileParser.py
SmslsUtils/DataTools/__init__.py
SmslsUtils/MalsRecorder/MalsCard.py
SmslsUtils/MalsRecorder/MalsDataCollector.py
SmslsUtils/MalsRecorder/MalsDataPlotter.py
SmslsUtils/MalsRecorder/SerialUtils.py
SmslsUtils/MalsRecorder/__init__.py
SmslsUtils/MalsRecorder/__main__.py
SmslsUtils/SmslsDevicePy/SmslsCamera.dll
SmslsUtils/SmslsDevicePy/SmslsDeviceCommon.dll
SmslsUtils/SmslsDevicePy/SmslsDeviceCs.dll
SmslsUtils/SmslsDevicePy/SmslsDevicePy.py
SmslsUtils/SmslsDevicePy/SmslsInputOutput.dll
SmslsUtils/SmslsDevicePy/SmslsServo.dll
SmslsUtils/SmslsDevicePy/SmslsStepper.dll
SmslsUtils/SmslsDevicePy/SmslsTemperature.dll
SmslsUtils/SmslsDevicePy/_SmslsDevicePy.pyd
SmslsUtils/SmslsDevicePy/__init__.py
SmslsUtils/SmslsDevicePy/ftbusui.dll
SmslsUtils/SmslsDevicePy/ftcserco.dll
SmslsUtils/SmslsDevicePy/ftd2xx.dll
SmslsUtils/SmslsDevicePy/ftlang.dll
SmslsUtils/SmslsDevicePy/ftserui2.dll
SmslsUtils/SmslsDevicePy/hidapi.dll
SmslsUtils/SmslsDevicePy/libusb0.dll
SmslsUtils/SmslsDevicePy/modbus.dll
SmslsUtils/SmslsDevicePy/phidget21.dll
SmslsUtils/SmslsTron/SmslsTron.py
SmslsUtils/SmslsTron/__init__.py
SmslsUtils/SmslsTron/__main__.py