Metadata-Version: 1.1
Name: SmslsUtils
Version: 0.10.0.29
Summary: This package provides utility functions for working with ARGEN/SMSLS data and systems.
Home-page: https://bitbucket.org/apmtinc/smslsutils
Author: Fluence Analytics
Author-email: watson.boyett@fluenceanalytics.com
License: GNU GPL v3
Keywords: ARGEN SMSLS Fluence
Platform: UNKNOWN
Classifier: Development Status :: 3 - Alpha
Classifier: Environment :: Win32 (MS Windows)
Classifier: Operating System :: Microsoft :: Windows
Classifier: Intended Audience :: Science/Research
Classifier: Natural Language :: English
Classifier: Programming Language :: Python
Classifier: Programming Language :: Python :: 3
Classifier: Topic :: Scientific/Engineering
Classifier: Topic :: Utilities
